fixedeffect/__init__.py
fixedeffect/_version.py
fixedeffect/btwng/__init__.py
fixedeffect/btwng/btwng.py
fixedeffect/fe/__init__.py
fixedeffect/fe/did.py
fixedeffect/fe/fe.py
fixedeffect/fe/getfe.py
fixedeffect/iv/__init__.py
fixedeffect/iv/iv.py
fixedeffect/iv/ivgmm.py
fixedeffect/iv/ivtest.py
fixedeffect/multi_model/__init__.py
fixedeffect/multi_model/multi_model.py
fixedeffect/utils/CalDf.py
fixedeffect/utils/CalFullModel.py
fixedeffect/utils/ClusterErr.py
fixedeffect/utils/DemeanDataframe.py
fixedeffect/utils/Forg.py
fixedeffect/utils/FormTransfer.py
fixedeffect/utils/GenCrossProd.py
fixedeffect/utils/OLSFixed.py
fixedeffect/utils/Operation.py
fixedeffect/utils/Projection.py
fixedeffect/utils/RobustErr.py
fixedeffect/utils/TableFormat.py
fixedeffect/utils/WaldTest.py
fixedeffect/utils/__init__.py
fixedeffect/utils/panel_dgp.py
fixedeffect/utils/to_latex.py
utils/__init__.py
utils/panel_dgp.py
FixedEffectModel-0.0.5.dist-info/LICENSE.txt
FixedEffectModel-0.0.5.dist-info/METADATA
FixedEffectModel-0.0.5.dist-info/WHEEL
FixedEffectModel-0.0.5.dist-info/top_level.txt
FixedEffectModel-0.0.5.dist-info/RECORD
