Metadata-Version: 2.1
Name: FixedEffectModel
Version: 0.0.5
Summary: Solutions to linear model with high dimensional fixed effects.
Home-page: https://github.com/ksecology/FixedEffectModel
Author: ksecology
Author-email: da_ecology@kuaishou.com
License: MIT
Platform: UNKNOWN
Classifier: Development Status :: 3 - Alpha
Classifier: License :: OSI Approved :: MIT License
Classifier: Topic :: Scientific/Engineering :: Mathematics
Classifier: Topic :: Sociology
Classifier: Topic :: Scientific/Engineering :: Information Analysis
Classifier: Programming Language :: Python :: 3
Classifier: Programming Language :: Python :: 3.6
Classifier: Programming Language :: Python :: 3.7
Classifier: Programming Language :: Python :: 3.8
Classifier: Operating System :: OS Independent
Requires-Python: >=3.6
License-File: LICENSE.txt
Requires-Dist: pandas (>=0.16.0)
Requires-Dist: numpy (>=1.9.2)
Requires-Dist: scipy (>=1.6.0)
Requires-Dist: statsmodels (>=0.12.2)
Requires-Dist: networkx (>=2.5)
